promptools-0.1.3.6.dist-info/METADATA
promptools-0.1.3.6.dist-info/WHEEL
promptools-0.1.3.6.dist-info/entry_points.txt
promptools/__init__.py
promptools/extractors/__init__.py
promptools/extractors/json.py
promptools/extractors/json.pyi
promptools/extractors/validate.py
promptools/extractors/validate.pyi
promptools/openai/__init__.py
promptools/openai/tokenize.py
promptools/openai/tokenize.pyi
promptools/stream/sse.py
promptools/stream/sse.pyi
promptools-0.1.3.6.dist-info/RECORD
