Metadata-Version: 2.1
Name: promptools
Version: 0.1.3.6
Summary: useful utilities for prompt engineering
Author-Email: Muspi Merol <me@promplate.dev>
License: MIT
Classifier: Typing :: Typed
Classifier: Framework :: Pydantic :: 2
Classifier: Topic :: Utilities
Classifier: Topic :: File Formats :: JSON
Classifier: Topic :: Text Processing
Classifier: Topic :: Text Processing :: Markup
Classifier: Topic :: Text Processing :: Markup :: Markdown
Classifier: Operating System :: OS Independent
Requires-Python: >=3.8
Requires-Dist: partial-json-parser<0.3,>=0.2.1
Provides-Extra: validation
Requires-Dist: pydantic<3; extra == "validation"
Provides-Extra: tokenizer
Requires-Dist: tiktoken~=0.3; extra == "tokenizer"
Provides-Extra: stream
Requires-Dist: promplate~=0.3; extra == "stream"
Requires-Dist: attrs>=23; extra == "stream"
